pycnfg/__init__.py
pycnfg/__version__.py
pycnfg/default.py
pycnfg/handler.py
pycnfg/producer.py
pycnfg/utils.py
pycnfg-0.0.2.dist-info/METADATA
pycnfg-0.0.2.dist-info/WHEEL
pycnfg-0.0.2.dist-info/top_level.txt
pycnfg-0.0.2.dist-info/RECORD
