Metadata-Version: 2.1
Name: pycnfg
Version: 0.0.2
Summary: Flexible Python configurations.
Home-page: https://github.com/nizaevka/pycnfg
Author: nizaevka
Author-email: knizaev@gmail.com
License: UNKNOWN
Project-URL: Documentation, https://pycnfg.readthedocs.io/
Project-URL: Source, https://github.com/nizaevka/pycnfg
Project-URL: Tracker, https://github.com/nizaevka/pycnfg/issues
Keywords: configuration
Platform: UNKNOWN
Classifier: Development Status :: 4 - Beta
Classifier: Programming Language :: Python :: 3
Classifier: License :: OSI Approved :: Apache Software License
Classifier: Operating System :: OS Independent
Requires-Python: >=3.6
Provides-Extra: dev
Requires-Dist: pytest (==5.4.3) ; extra == 'dev'
Requires-Dist: sphinx (==3.1.2) ; extra == 'dev'
Requires-Dist: sphinxcontrib-napoleon ; extra == 'dev'
Requires-Dist: sphinx-autodoc-typehints ; extra == 'dev'
Requires-Dist: sphinx-rtd-theme ; extra == 'dev'
Requires-Dist: numpydoc ; extra == 'dev'
Requires-Dist: coverage ; extra == 'dev'
